tgclients/__init__.py
tgclients/aggregator.py
tgclients/auth.py
tgclients/config.py
tgclients/crud.py
tgclients/metadata.py
tgclients/mime.types
tgclients/publish.py
tgclients/py.typed
tgclients/search.py
tgclients/tgfilenames.rules
tgclients/utils.py
tgclients/databinding/__init__.py
tgclients/databinding/rdf.py
tgclients/databinding/textgrid_metadata_2010.py
tgclients/databinding/textgrid_metadata_agent_2010.py
tgclients/databinding/textgrid_metadata_script_2010.py
tgclients/databinding/tgsearch.py
tgclients/databinding/tgpublish/__init__.py
tgclients/databinding/tgpublish/tgpub.py
tgclients/templates/aggregation.xml.jinja2
tgclients/templates/aggregation.xml.jinja2.license
tgclients/templates/metadata.xml.jinja2
tgclients/templates/metadata.xml.jinja2.license
tgclients-0.24.0.dist-info/licenses/LICENSE
tgclients-0.24.0.dist-info/METADATA
tgclients-0.24.0.dist-info/WHEEL
tgclients-0.24.0.dist-info/top_level.txt
tgclients-0.24.0.dist-info/RECORD
